{
  "type": "create:mechanical_crafting",
  "accept_mirrored": true,
  "category": "misc",
  "key": {
    "A": {
      "item": "allthemodium:unobtainium_vibranium_alloy_ingot"
    },
    "V": {
      "item": "tfmg:cast_iron_chemical_vat"
    },
    "C": {
      "item": "create:brass_casing"
    },
    "m": {
      "item": "create:precision_mechanism"
    },
    "s": {
      "item": "tfmg:steel_mechanism"
    },
    "e": {
      "item": "create:electron_tube"
    }
  },
  "pattern": [
    "AsA",
    "mVm",
    "CeC"
  ],
  "result": {
    "count": 1,
    "id": "create:creative_crate"
  }
}
